{"chunk_definitions":[{"row":22,"row_count":1,"visible":true,"expansion_state":0,"options":{"engine":"r","label":"setup","include":false,"dev":"png"},"document_id":"7A599521","chunk_id":"csetup_chunk","chunk_label":"setup"},{"row":36,"row_count":1,"visible":true,"expansion_state":0,"options":{"engine":"r","show":false,"label":"unnamed-chunk-2","dev":"png"},"document_id":"7A599521","chunk_id":"cxa919clpd4ie","chunk_label":"unnamed-chunk-1"},{"row":42,"row_count":1,"visible":true,"expansion_state":0,"options":{"engine":"r","label":"unnamed-chunk-3","dev":"png"},"document_id":"7A599521","chunk_id":"cqfnp6uwk7mfa","chunk_label":"unnamed-chunk-2"},{"row":52,"row_count":1,"visible":true,"expansion_state":0,"options":{"engine":"r","label":"Clean columns ","dev":"png"},"document_id":"7A599521","chunk_id":"cpsqjm24c5b0o","chunk_label":"Clean columns"},{"row":88,"row_count":1,"visible":true,"expansion_state":0,"options":{"engine":"r","label":"unnamed-chunk-4","dev":"png"},"document_id":"7A599521","chunk_id":"c3y6489lva5ur","chunk_label":"unnamed-chunk-3"},{"row":459,"row_count":1,"visible":true,"expansion_state":0,"options":{"engine":"r","label":"unnamed-chunk-13","dev":"png"},"document_id":"7A599521","chunk_id":"cdd86l417n5oc","chunk_label":"unnamed-chunk-16"},{"row":488,"row_count":1,"visible":true,"expansion_state":0,"options":{"engine":"r","warning":false,"label":"unnamed-chunk-14","dev":"png"},"document_id":"7A599521","chunk_id":"c1sqsyjra5uzw","chunk_label":"unnamed-chunk-17"},{"row":570,"row_count":1,"visible":true,"expansion_state":0,"options":{"engine":"r","label":"unnamed-chunk-18","dev":"png"},"document_id":"7A599521","chunk_id":"ceoyni08s17fa","chunk_label":"unnamed-chunk-18"},{"row":592,"row_count":1,"visible":true,"expansion_state":0,"options":{"engine":"r","label":"unnamed-chunk-19","dev":"png"},"document_id":"7A599521","chunk_id":"cmbci63yp7bqi","chunk_label":"unnamed-chunk-19"},{"row":625,"row_count":1,"visible":true,"expansion_state":0,"options":{"engine":"r","label":"unnamed-chunk-20","dev":"png"},"document_id":"7A599521","chunk_id":"cw8ad3q86ywo2","chunk_label":"unnamed-chunk-20"},{"row":698,"row_count":1,"visible":true,"expansion_state":0,"options":{"engine":"r","label":"unnamed-chunk-15","dev":"png"},"document_id":"7A599521","chunk_id":"cl9mzuzm1pfnc","chunk_label":"unnamed-chunk-22"},{"row":720,"row_count":1,"visible":true,"expansion_state":0,"options":{"engine":"r","label":"unnamed-chunk-16","dev":"png"},"document_id":"7A599521","chunk_id":"cu4lm2yxczkqb","chunk_label":"unnamed-chunk-23"},{"row":753,"row_count":1,"visible":true,"expansion_state":0,"options":{"engine":"r","label":"unnamed-chunk-17","dev":"png"},"document_id":"7A599521","chunk_id":"ckqcq44tyj1va","chunk_label":"unnamed-chunk-24"},{"row":855,"row_count":1,"visible":true,"expansion_state":0,"options":{"engine":"r","label":"unnamed-chunk-34","dev":"png"},"document_id":"7A599521","chunk_id":"ccz28bma0msqk","chunk_label":"unnamed-chunk-25"},{"row":917,"row_count":1,"visible":true,"expansion_state":0,"options":{"engine":"r","label":"Publication per depth by latitudinalRegion","dev":"png"},"document_id":"7A599521","chunk_id":"c6et1dpqmh599","chunk_label":"Publication per depth by latitudinalRegion"},{"row":944,"row_count":1,"visible":true,"expansion_state":0,"options":{"engine":"r","label":"Create a platform by depth data frame and keep meso_samplingPlatform","dev":"png"},"document_id":"7A599521","chunk_id":"cw5hg531a6dxf","chunk_label":"Create a platform by depth data frame and keep meso_samplingPlatform"},{"row":976,"row_count":1,"visible":true,"expansion_state":0,"options":{"engine":"r","label":"Split the platform column in one binary column per platform  ","dev":"png"},"document_id":"7A599521","chunk_id":"cmeu2nfvr88rr","chunk_label":"Split the platform column in one binary column per platform"},{"row":993,"row_count":1,"visible":true,"expansion_state":0,"options":{"engine":"r","label":"Create a summary table with # studies per platform ","dev":"png"},"document_id":"7A599521","chunk_id":"chpn6z2dsreg3","chunk_label":"Create a summary table with # studies per platform"},{"row":1009,"row_count":1,"visible":true,"expansion_state":0,"options":{"engine":"r","label":"Create a column with the number of platforms per study","dev":"png"},"document_id":"7A599521","chunk_id":"cq6d97dmr84nc","chunk_label":"Create a column with the number of platforms per study"},{"row":1020,"row_count":1,"visible":true,"expansion_state":0,"options":{"engine":"r","label":"Calculate number of records by number of platforms in %","dev":"png"},"document_id":"7A599521","chunk_id":"c0a8lxzl78qwo","chunk_label":"Calculate number of records by number of platforms in %"},{"row":1033,"row_count":1,"visible":true,"expansion_state":0,"options":{"engine":"r","label":"unnamed-chunk-4","dev":"png"},"document_id":"7A599521","chunk_id":"c8sms3rvu89dz","chunk_label":"unnamed-chunk-27"},{"row":1058,"row_count":1,"visible":true,"expansion_state":0,"options":{"engine":"r","label":"set max_depth to mesophotic limits","warning":false,"dev":"png"},"document_id":"7A599521","chunk_id":"ckj55xfzw469t","chunk_label":"set max_depth to mesophotic limits"},{"row":1077,"row_count":1,"visible":true,"expansion_state":0,"options":{"engine":"r","label":"set min_depth to mesophotic limits","dev":"png"},"document_id":"7A599521","chunk_id":"cl4chjfdb26kp","chunk_label":"set min_depth to mesophotic limits"},{"row":1114,"row_count":1,"visible":true,"expansion_state":0,"options":{"engine":"r","label":"unnamed-chunk-5","dev":"png"},"document_id":"7A599521","chunk_id":"cs9a13oaf3ape","chunk_label":"unnamed-chunk-28"},{"row":1124,"row_count":1,"visible":true,"expansion_state":0,"options":{"engine":"r","label":"unnamed-chunk-6","dev":"png"},"document_id":"7A599521","chunk_id":"cbefzio3erzms","chunk_label":"unnamed-chunk-29"},{"row":1138,"row_count":1,"visible":true,"expansion_state":0,"options":{"engine":"r","label":"unnamed-chunk-7","dev":"png"},"document_id":"7A599521","chunk_id":"ccje857e2ma24","chunk_label":"unnamed-chunk-30"},{"row":1153,"row_count":1,"visible":true,"expansion_state":0,"options":{"engine":"r","label":"Add visual column to reorder platform","dev":"png"},"document_id":"7A599521","chunk_id":"cpz3p29hku8v4","chunk_label":"Add visual column to reorder platform"},{"row":1202,"row_count":1,"visible":true,"expansion_state":0,"options":{"engine":"r","label":"Create a bar plot with depth bins by platform and latitudinalRegion","dev":"png"},"document_id":"7A599521","chunk_id":"clh95i13i5hha","chunk_label":"platform_depth_lat_plot barplot"},{"row":1248,"row_count":1,"visible":true,"expansion_state":0,"options":{"engine":"r","label":"dir_ind_by_decade","dev":"png"},"document_id":"7A599521","chunk_id":"cf8ufj1jsazmw","chunk_label":"dir_ind_by_decade"},{"row":1440,"row_count":1,"visible":true,"expansion_state":0,"options":{"engine":"r","label":"Clean field_merged data frame ","dev":"png"},"document_id":"7A599521","chunk_id":"ctcrjfuujgsk7","chunk_label":"Clean field_merged data frame"},{"row":1454,"row_count":1,"visible":true,"expansion_state":0,"options":{"engine":"r","label":"Select only the most common fields ","dev":"png"},"document_id":"7A599521","chunk_id":"crtbil5nlsisz","chunk_label":"Select only the most common fields"},{"row":1471,"row_count":1,"visible":true,"expansion_state":0,"options":{"engine":"r","label":"Rename fields with long version names","dev":"png"},"document_id":"7A599521","chunk_id":"cwd8q5vkcbt3m","chunk_label":"Rename fields with long version names"},{"row":1477,"row_count":1,"visible":true,"expansion_state":0,"options":{"engine":"r","label":"unnamed-chunk-31","dev":"png"},"document_id":"7A599521","chunk_id":"c5nb6b6ggz8se","chunk_label":"unnamed-chunk-33"},{"row":1491,"row_count":1,"visible":true,"expansion_state":0,"options":{"engine":"r","label":"Select only the most common indicators","dev":"png"},"document_id":"7A599521","chunk_id":"cwfowxmcybubk","chunk_label":"Select only the most common indicators"},{"row":1500,"row_count":1,"visible":true,"expansion_state":0,"options":{"engine":"r","label":"unnamed-chunk-32","dev":"png"},"document_id":"7A599521","chunk_id":"c6xwcrq182xcl","chunk_label":"unnamed-chunk-34"},{"row":1525,"row_count":1,"visible":true,"expansion_state":0,"options":{"engine":"r","label":"unnamed-chunk-33","dev":"png"},"document_id":"7A599521","chunk_id":"cbiimnuszar72","chunk_label":"unnamed-chunk-35"},{"row":1531,"row_count":1,"visible":true,"expansion_state":0,"options":{"engine":"r","label":"Multiply the transpose of the field matrix with the indicator matrix","dev":"png"},"document_id":"7A599521","chunk_id":"cyz6ie54qaqkw","chunk_label":"Multiply the transpose of the field matrix with the indicator matrix"},{"row":1539,"row_count":1,"visible":true,"expansion_state":0,"options":{"engine":"r","label":"reshape the co-occurrence matrix for plotting","dev":"png"},"document_id":"7A599521","chunk_id":"cqog89zb11d1u","chunk_label":"reshape the co-occurrence matrix for plotting"},{"row":1552,"row_count":1,"visible":true,"expansion_state":0,"options":{"engine":"r","label":"Plot the heatmap","dev":"png"},"document_id":"7A599521","chunk_id":"cdvs6mfhgdast","chunk_label":"Plot the heatmap"},{"row":1560,"row_count":1,"visible":true,"expansion_state":0,"options":{"engine":"r","label":"export field_ind_heat","dev":"png"},"document_id":"7A599521","chunk_id":"cwyigb7iwtshb","chunk_label":"export field_ind_heat"},{"row":1573,"row_count":1,"visible":true,"expansion_state":0,"options":{"engine":"r","label":"ecological indicicators per record","dev":"png"},"document_id":"7A599521","chunk_id":"c89h72mcg84wg","chunk_label":"ecological indicicators per record"},{"row":1586,"row_count":1,"visible":true,"expansion_state":0,"options":{"engine":"r","label":"unnamed-chunk-21","dev":"png"},"document_id":"7A599521","chunk_id":"cq8usnlj0n5ne","chunk_label":"unnamed-chunk-36"},{"row":1791,"row_count":1,"visible":true,"expansion_state":0,"options":{"engine":"r","label":"unnamed-chunk-16","dev":"png"},"document_id":"7A599521","chunk_id":"cgny3hbzbup6o","chunk_label":"unnamed-chunk-38"},{"row":2226,"row_count":1,"visible":true,"expansion_state":0,"options":{"engine":"r","label":"unnamed-chunk-5","dev":"png"},"document_id":"085AA2D6","chunk_id":"cv4emuwowrg5h","chunk_label":"unnamed-chunk-44"},{"row":2538,"row_count":1,"visible":true,"expansion_state":0,"options":{"engine":"r","label":"unnamed-chunk-67","dev":"png"},"document_id":"7A599521","chunk_id":"cfl1wjxz8ggbk","chunk_label":"unnamed-chunk-54"},{"row":2676,"row_count":1,"visible":true,"expansion_state":0,"options":{"engine":"r","label":"unnamed-chunk-69","dev":"png"},"document_id":"7A599521","chunk_id":"cibki1xo3y4sm","chunk_label":"unnamed-chunk-59"},{"row":2682,"row_count":1,"visible":true,"expansion_state":0,"options":{"engine":"r","label":"unnamed-chunk-39","dev":"png"},"document_id":"7A599521","chunk_id":"c2r2pvsrgzcwz","chunk_label":"unnamed-chunk-60"},{"row":2694,"row_count":1,"visible":true,"expansion_state":0,"options":{"engine":"r","label":"unnamed-chunk-46","dev":"png"},"document_id":"7A599521","chunk_id":"cc875y8c5nwat","chunk_label":"unnamed-chunk-62"},{"row":2730,"row_count":1,"visible":true,"expansion_state":0,"options":{"engine":"r","label":"unnamed-chunk-47","dev":"png"},"document_id":"7A599521","chunk_id":"c14kg7gji505b","chunk_label":"unnamed-chunk-69"},{"row":2779,"row_count":1,"visible":true,"expansion_state":0,"options":{"engine":"r","label":"Molecular techniques in non-taxonomic studies","dev":"png"},"document_id":"7A599521","chunk_id":"crcyvms6addda","chunk_label":"Molecular techniques in non-taxonomic studies"},{"row":2795,"row_count":1,"visible":true,"expansion_state":0,"options":{"engine":"r","label":"unnamed-chunk-15","dev":"png"},"document_id":"7A599521","chunk_id":"c8osktycqftwc","chunk_label":"unnamed-chunk-72"}],"doc_write_time":1774953515,"working_dir":null,"default_chunk_options":{"echo":true,"tidy":"styler"},"chunk_rendered_width":700}